binotel/__init__.py
binotel/app.py
tests/__init__.py
binotel-0.0.1.dist-info/LICENSE
binotel-0.0.1.dist-info/METADATA
binotel-0.0.1.dist-info/WHEEL
binotel-0.0.1.dist-info/top_level.txt
binotel-0.0.1.dist-info/RECORD
