Metadata-Version: 2.1
Name: binotel
Version: 0.0.1
Summary: This package provides Python implementation of some Binotel api. 
Home-page: https://github.com/srostyslav/binotel
Author: Rostyslav
Author-email: rostyslav.rigroup@gmail.com
License: UNKNOWN
Platform: UNKNOWN
Classifier: Programming Language :: Python :: 3
Classifier: License :: OSI Approved :: MIT License
Classifier: Operating System :: OS Independent
Requires-Python: >=3.6
License-File: LICENSE
